LICENSE
MANIFEST.in
README
setup.py
pygwidgets/__init__.py
pygwidgets/conf.py
pygwidgets/pygwidgets.py
pygwidgets.egg-info/PKG-INFO
pygwidgets.egg-info/SOURCES.txt
pygwidgets.egg-info/dependency_links.txt
pygwidgets.egg-info/requires.txt
pygwidgets.egg-info/top_level.txt
pygwidgets_test/Main_Test_pygwidgets.py
pygwidgets_test/__init__.py
pygwidgets_test/images/background.jpg
pygwidgets_test/images/checkBoxOff.png
pygwidgets_test/images/checkBoxOffDisabled.png
pygwidgets_test/images/checkBoxOffDown.png
pygwidgets_test/images/checkBoxOn.png
pygwidgets_test/images/checkBoxOnDisabled.png
pygwidgets_test/images/checkBoxOnDown.png
pygwidgets_test/images/dragMeDisabled.png
pygwidgets_test/images/dragMeDown.png
pygwidgets_test/images/dragMeOver.png
pygwidgets_test/images/dragMeUp.png
pygwidgets_test/images/extenDisabled.png
pygwidgets_test/images/frisbee.png
pygwidgets_test/images/imageDown.jpg
pygwidgets_test/images/imageLeft.jpg
pygwidgets_test/images/imageRight.jpg
pygwidgets_test/images/imageStart.jpg
pygwidgets_test/images/imageUp.jpg
pygwidgets_test/images/pythonIcon.png
pygwidgets_test/images/radioHighOff.png
pygwidgets_test/images/radioHighOffDisabled.png
pygwidgets_test/images/radioHighOffDown.png
pygwidgets_test/images/radioHighOn.png
pygwidgets_test/images/radioHighOnDisabled.png
pygwidgets_test/images/radioHighOnDown.png
pygwidgets_test/images/radioLowOff.png
pygwidgets_test/images/radioLowOffDisabled.png
pygwidgets_test/images/radioLowOffDown.png
pygwidgets_test/images/radioLowOn.png
pygwidgets_test/images/radioLowOnDisabled.png
pygwidgets_test/images/radioLowOnDown.png
pygwidgets_test/images/radioMedOff.png
pygwidgets_test/images/radioMedOffDisabled.png
pygwidgets_test/images/radioMedOffDown.png
pygwidgets_test/images/radioMedOn.png
pygwidgets_test/images/radioMedOnDisabled.png
pygwidgets_test/images/radioMedOnDown.png
pygwidgets_test/images/restartButtonDisabled.png
pygwidgets_test/images/restartButtonDown.png
pygwidgets_test/images/restartButtonOver.png
pygwidgets_test/images/restartButtonUp.png
pygwidgets_test/images/sliderExtent.png
pygwidgets_test/images/sliderExtentDisabled.png
pygwidgets_test/images/sliderThumb.png
