Metadata-Version: 2.1
Name: pygwidgets
Version: 1.1.2
Summary: User interface widgets for use with Pygame
Home-page: https://github.com/IrvKalb/pygwidgets
Author: Irv Kalb
Author-email: Irv@furrypants.com
License: BSD
Keywords: pygame widgets user interface buttons text dragger animation image
Classifier: Programming Language :: Python :: 3
Classifier: License :: OSI Approved :: BSD License
Classifier: Operating System :: OS Independent
License-File: LICENSE
